{
  "Guest" : {
    "denied" : {},
    "Home" : ["*"],
    "Products" : ["*"],
    "Cart" : ["*"],
    "Register" : ["login", "register"],
    "Restricted" : ["*"],
    "Categories" : ["*"]
  },
  "LoggedIn" : {
    "denied" : {
      "Register" : ["login", "register"],
      "Menu" : ["*"]
    },
    "Register" : ["logout"]
  },
  "SuperAdmin" : {
    "denied" : {
      "Menu" : ["*"]
    },
    "Admindashboard" : ["*"],
    "Adminsales" : ["*"],
    "Adminproducts" : ["*"],
    "Adminbrands" : ["*"]
  },
  "Host" : {
    "denied" : {},
    "Admindashboard" : ["*"],
    "Adminsales" : ["*"],
    "Adminproducts" : ["*"],
    "Adminbrands" : ["*"],
    "Menu" : ["*"]
  }
}
